irisml/tasks/append_classifier.py
irisml/tasks/benchmark_dataset.py
irisml/tasks/benchmark_model.py
irisml/tasks/benchmark_model_with_grad_cache.py
irisml/tasks/build_classification_prompt_dataset.py
irisml/tasks/build_zero_shot_classifier.py
irisml/tasks/concatenate_datasets.py
irisml/tasks/convert_classification_predictions_to_key_value_pair.py
irisml/tasks/convert_document_intelligence_read_predictions_to_image_metadata.py
irisml/tasks/convert_key_value_pair_schema_to_structured_output_schema.py
irisml/tasks/convert_key_value_pairs_to_key_value_pair_labels.py
irisml/tasks/convert_relative_to_absolute_coordinates.py
irisml/tasks/convert_vqa_dataset_to_image_text_classification_dataset.py
irisml/tasks/create_classification_prompt_generator.py
irisml/tasks/create_prompt_generator.py
irisml/tasks/create_round_resize_transform.py
irisml/tasks/evaluate_accuracy.py
irisml/tasks/evaluate_captioning.py
irisml/tasks/evaluate_detection_average_precision.py
irisml/tasks/evaluate_image_text_retrieval.py
irisml/tasks/evaluate_phrase_grounding.py
irisml/tasks/evaluate_phrase_grounding_recall.py
irisml/tasks/evaluate_string_matching_accuracy.py
irisml/tasks/exclude_negative_samples_from_classification_dataset.py
irisml/tasks/export_coco_from_torch_dataset.py
irisml/tasks/export_onnx.py
irisml/tasks/extract_images_from_key_value_dataset_transform.py
irisml/tasks/extract_val_by_key_from_jsonl.py
irisml/tasks/find_incorrect_classification_indices.py
irisml/tasks/find_incorrect_classification_multilabel_indices.py
irisml/tasks/flatten_captioning_dataset.py
irisml/tasks/get_questions_from_vqa_dataset.py
irisml/tasks/get_subclass_dataset.py
irisml/tasks/get_targets_from_dataset.py
irisml/tasks/inject_image_metadata_to_key_value_pair_dataset.py
irisml/tasks/load_jsonl_vqa_dataset.py
irisml/tasks/load_simple_classification_dataset.py
irisml/tasks/make_classification_dataset_from_key_value_pair.py
irisml/tasks/make_classification_dataset_from_object_detection.py
irisml_tasks_training-0.0.132.dist-info/LICENSE
irisml_tasks_training-0.0.132.dist-info/METADATA
irisml_tasks_training-0.0.132.dist-info/WHEEL
irisml_tasks_training-0.0.132.dist-info/top_level.txt
irisml_tasks_training-0.0.132.dist-info/RECORD
