Metadata-Version: 2.1
Name: irisml-tasks-training
Version: 0.0.132
Summary: IrisML tasks for pytorch training
Home-page: https://github.com/microsoft/irisml-tasks-training
Author: irisdev
License: MIT
Requires-Python: >=3.8
License-File: LICENSE
Requires-Dist: irisml
Requires-Dist: onnx
Requires-Dist: Pillow
Requires-Dist: scikit-learn
Requires-Dist: torch
Requires-Dist: torchvision
Requires-Dist: tqdm
Provides-Extra: azureml
Requires-Dist: azureml-mlflow ; extra == 'azureml'
Requires-Dist: mlflow-skinny ; extra == 'azureml'
Provides-Extra: ipex
Requires-Dist: intel-extension-for-pytorch ; extra == 'ipex'
